pysleigh/cli/__init__.py
pysleigh/cli/benchmark.py
pysleigh/cli/fetch.py
pysleigh/cli/generate.py
pysleigh/cli/main.py
pysleigh/cli/prep.py
pysleigh/cli/run.py
pysleigh/cli/submit.py
pysleigh/modules/__init__.py
pysleigh/modules/answers.py
pysleigh/modules/article.py
pysleigh/modules/benchmark.py
pysleigh/modules/generate_solution.py
pysleigh/modules/generate_test.py
pysleigh/modules/input.py
pysleigh/modules/run_solution.py
pysleigh/modules/run_test.py
pysleigh/modules/submit_solution.py
pysleigh/utilities/__init__.py
pysleigh/utilities/config.py
pysleigh/utilities/date.py
pysleigh/utilities/logger.py
pysleigh/utilities/session.py
pysleigh-0.1.2.dist-info/METADATA
pysleigh-0.1.2.dist-info/WHEEL
pysleigh-0.1.2.dist-info/entry_points.txt
pysleigh-0.1.2.dist-info/top_level.txt
pysleigh-0.1.2.dist-info/RECORD
