Metadata-Version: 2.4
Name: pysleigh
Version: 0.1.2
Summary: A CLI tool for Advent of Code automation
Author-email: David Bateman <148539956+Dheebz@users.noreply.github.com>
License: MIT
Requires-Python: >=3.8
Requires-Dist: beautifulsoup4
Requires-Dist: markdownify
Requires-Dist: requests
Requires-Dist: typer[all]
Requires-Dist: toml
Requires-Dist: pytest
Provides-Extra: dev
Requires-Dist: black; extra == "dev"
Requires-Dist: ruff; extra == "dev"
Requires-Dist: mypy; extra == "dev"
Requires-Dist: pytest-cov; extra == "dev"
